{"name":"As a user I can\u0027t get product comments without path","id":"get-product-comments;as-a-user-i-can-t-get-product-comments-without-path","testSteps":[{"number":1,"description":"Given I set API endpoint for get product comments without the path","duration":1,"startTime":"2023-11-03T19:14:38.244957+07:00[Asia/Jakarta]","result":"SUCCESS","precondition":false,"level":0,"children":[{"number":2,"description":"I set API endpoint for get product comments without the path","duration":0,"startTime":"2023-11-03T19:14:38.246223+07:00[Asia/Jakarta]","result":"SUCCESS","precondition":false,"level":1}]},{"number":3,"description":"When I send request to get product comments no path","duration":178,"startTime":"2023-11-03T19:14:38.246983+07:00[Asia/Jakarta]","result":"SUCCESS","precondition":false,"level":0,"children":[{"number":4,"description":"I send request to get product comments no path","duration":177,"startTime":"2023-11-03T19:14:38.247229+07:00[Asia/Jakarta]","result":"SUCCESS","precondition":false,"level":1,"children":[{"number":5,"description":"I set API endpoint for get product comments without the path","duration":0,"startTime":"2023-11-03T19:14:38.247631+07:00[Asia/Jakarta]","result":"SUCCESS","precondition":false,"level":2},{"number":6,"description":"GET https://altashop-api.fly.dev/api","duration":0,"startTime":"2023-11-03T19:14:38.424841+07:00[Asia/Jakarta]","result":"SUCCESS","restQuery":{"method":"GET","path":"https://altashop-api.fly.dev/api","content":"","contentType":"null","requestHeaders":"Accept\u003d*/*","requestCookies":"","responseHeaders":"date: Fri, 03 Nov 2023 12:14:38 GMT\ncontent-encoding: gzip\ncontent-type: text/plain; charset\u003dutf-8\ntransfer-encoding: chunked\nserver: Fly/7328d5b5 (2023-10-27)\nvia: 1.1 fly.io\nfly-request-id: 01HEAHPNAVHWJT516GQX6FMNAJ-sin","responseCookies":"","responseBody":"not found\n","statusCode":404},"precondition":false,"level":2}]}]},{"number":7,"description":"Then I received status code 404 Not Found in request to get product comments","duration":0,"startTime":"2023-11-03T19:14:38.425544+07:00[Asia/Jakarta]","result":"SUCCESS","precondition":false,"level":0,"children":[{"number":8,"description":"I received status code 404 Not Found in request to get product comments","duration":0,"startTime":"2023-11-03T19:14:38.425820+07:00[Asia/Jakarta]","result":"SUCCESS","precondition":false,"level":1}]},{"number":9,"description":"And I received message error \"record not found\" get product comments response","duration":0,"startTime":"2023-11-03T19:14:38.426559+07:00[Asia/Jakarta]","result":"SUCCESS","precondition":false,"level":0,"children":[{"number":10,"description":"I received message error \"record not found\" get product comments response","duration":0,"startTime":"2023-11-03T19:14:38.426749+07:00[Asia/Jakarta]","result":"SUCCESS","precondition":false,"level":1}]}],"userStory":{"id":"get-product-comments","storyName":"Get Product Comments","displayName":"Get Product Comments","path":"api/products/GetProductComments.feature","narrative":"  As a user\n  I want to get product comments\n  So that I can be get product comments","type":"feature","qualifiedTag":{"name":"Products/Get Product Comments","type":"feature","displayName":"Products/Get Product Comments"}},"featureTag":{"name":"Products/Get Product Comments","type":"feature","displayName":"Products/Get Product Comments"},"title":"As a user I can\u0027t get product comments without path","description":"","tags":[{"name":"Api/Products","type":"capability","displayName":"Products"},{"name":"Products/Get Product Comments","type":"feature","displayName":"Get Product Comments"},{"name":"Api","type":"theme","displayName":"Api"}],"allTags":[{"name":"Api/Products","type":"capability","displayName":"Products"},{"name":"Products/Get Product Comments","type":"feature","displayName":"Get Product Comments"},{"name":"Api","type":"theme","displayName":"Api"}],"startTime":"2023-11-03T19:14:38.243367+07:00[Asia/Jakarta]","duration":183,"projectKey":"","isManualTestingUpToDate":false,"context":"mac","manual":false,"testSource":"Cucumber","result":"SUCCESS"}